LICENSE.txt
MANIFEST.in
README.rst
fimport.py
setup.py
fimport.egg-info/PKG-INFO
fimport.egg-info/SOURCES.txt
fimport.egg-info/dependency_links.txt
fimport.egg-info/requires.txt
fimport.egg-info/top_level.txt
tests/test_fimport.py