Metadata-Version: 1.1
Name: fimport
Version: 0.2
Summary: Python Fortran import hook
Home-page: https://github.com/pv/fimport
Author: Pauli Virtanen
Author-email: pav@iki.fi
License: Apache
Platform: any
Classifier: Development Status :: 3 - Alpha
Classifier: Intended Audience :: Developers
Classifier: License :: OSI Approved :: Apache Software License
Classifier: Operating System :: OS Independent
Classifier: Programming Language :: Python
Classifier: Programming Language :: Python :: 2
Classifier: Programming Language :: Python :: 3
Classifier: Programming Language :: Fortran
